textualdon/Roadmap.md
textualdon/__init__.py
textualdon/__main__.py
textualdon/bars.py
textualdon/bs4_parser.py
textualdon/config.ini
textualdon/create_tables.sql
textualdon/css/bars.tcss
textualdon/css/main.tcss
textualdon/css/pages.tcss
textualdon/css/screens.tcss
textualdon/css/settings.tcss
textualdon/css/toot.tcss
textualdon/css/widgets.tcss
textualdon/error_handler.py
textualdon/html_templates.py
textualdon/imageviewer.py
textualdon/messages.py
textualdon/oauth.py
textualdon/pages.py
textualdon/proxy.py
textualdon/savedusers.py
textualdon/screens.py
textualdon/settings.py
textualdon/simplebutton.py
textualdon/sql.py
textualdon/toot.py
textualdon/tootbox.py
textualdon/tootscreens.py
textualdon/widgets.py
textualdon-0.1.4.dist-info/METADATA
textualdon-0.1.4.dist-info/WHEEL
textualdon-0.1.4.dist-info/entry_points.txt
textualdon-0.1.4.dist-info/RECORD
