Metadata-Version: 2.1
Name: textualdon
Version: 0.1.4
Summary: A Mastodon client built with the Textual framework
License: MIT
Author: edward-jazzhands
Author-email: ed.jazzhands@gmail.com
Requires-Python: >=3.12,<4.0
Classifier: License :: OSI Approved :: MIT License
Classifier: Programming Language :: Python :: 3
Classifier: Programming Language :: Python :: 3.12
Classifier: Programming Language :: Python :: 3.13
Requires-Dist: beautifulsoup4 (>=4.12.3,<5.0.0)
Requires-Dist: clipman (>=3.3.1,<4.0.0)
Requires-Dist: humanize (>=4.11.0,<5.0.0)
Requires-Dist: mastodon-py (>=1.8.1,<2.0.0)
Requires-Dist: platformdirs (>=4.3.6,<5.0.0)
Requires-Dist: pyperclip (>=1.9.0,<2.0.0)
Requires-Dist: textual-dev (>=1.6.1,<2.0.0)
Requires-Dist: textual-imageview (>=0.1.1,<0.2.0)
Requires-Dist: textual-pyfiglet (>=0.5.5,<0.6.0)
Requires-Dist: textual[syntax] (>=1.0.0,<2.0.0)
Requires-Dist: tzlocal (>=5.2,<6.0)
